pairtools/__init__.py
pairtools/__main__.py
pairtools/_logging.py
pairtools/lib/filterbycov.py
pairtools/lib/parse.py
pairtools/lib/phase.py
pairtools/lib/headerops.py
pairtools/lib/regions.cpython-311-x86_64-linux-gnu.so
pairtools/lib/stats.py
pairtools/lib/parse_pysam.pyx
pairtools/lib/regions.pyx
pairtools/lib/__init__.py
pairtools/lib/fileio.py
pairtools/lib/select.py
pairtools/lib/restrict.py
pairtools/lib/dedup_cython.cpython-311-x86_64-linux-gnu.so
pairtools/lib/parse_pysam.cpython-311-x86_64-linux-gnu.so
pairtools/lib/pairsio.py
pairtools/lib/dedup.py
pairtools/lib/pairsam_format.py
pairtools/lib/dedup_cython.pyx
pairtools/lib/scaling.py
pairtools/cli/filterbycov.py
pairtools/cli/parse.py
pairtools/cli/sample.py
pairtools/cli/phase.py
pairtools/cli/stats.py
pairtools/cli/split.py
pairtools/cli/__init__.py
pairtools/cli/select.py
pairtools/cli/merge.py
pairtools/cli/header.py
pairtools/cli/restrict.py
pairtools/cli/markasdup.py
pairtools/cli/flip.py
pairtools/cli/dedup.py
pairtools/cli/parse2.py
pairtools/cli/sort.py
pairtools/cli/scaling.py
pairtools.libs/libcsamfile-eb125f1f.cpython-311-x86_64-linux-gnu.so
pairtools.libs/libcbcf-bcfa9ae0.cpython-311-x86_64-linux-gnu.so
pairtools.libs/libcsamtools-304725ba.cpython-311-x86_64-linux-gnu.so
pairtools.libs/libctabixproxies-6206abf4.cpython-311-x86_64-linux-gnu.so
pairtools.libs/libcbcftools-17783b9d.cpython-311-x86_64-linux-gnu.so
pairtools.libs/libcfaidx-1616c151.cpython-311-x86_64-linux-gnu.so
pairtools.libs/libbz2-a273e504.so.1.0.6
pairtools.libs/liblzma-004595ca.so.5.2.2
pairtools.libs/libcutils-8d3d1f99.cpython-311-x86_64-linux-gnu.so
pairtools.libs/libctabix-fd17ebf7.cpython-311-x86_64-linux-gnu.so
pairtools.libs/libcvcf-83859c30.cpython-311-x86_64-linux-gnu.so
pairtools.libs/libchtslib-9d1ea776.cpython-311-x86_64-linux-gnu.so
pairtools-1.1.2.dist-info/top_level.txt
pairtools-1.1.2.dist-info/RECORD
pairtools-1.1.2.dist-info/LICENSE
pairtools-1.1.2.dist-info/entry_points.txt
pairtools-1.1.2.dist-info/METADATA
pairtools-1.1.2.dist-info/WHEEL
