Metadata-Version: 2.1
Name: pairtools
Version: 1.1.2
Summary: CLI tools to process mapped Hi-C data
Author-email: Open2C <open.chromosome.collective@gmail.com>
License: MIT License
Project-URL: Homepage, https://github.com/open2c/pairtools
Project-URL: Documentation, https://pairtools.readthedocs.io/en/latest/
Project-URL: Repository, https://github.com/open2c/pairtools.git
Project-URL: Issues, https://github.com/open2c/pairtools/issues
Project-URL: Changelog, https://github.com/open2c/pairtools/blob/master/CHANGES.md
Keywords: genomics,bioinformatics,Hi-C,contact,chromosome
Classifier: Development Status :: 5 - Production/Stable
Classifier: Intended Audience :: Science/Research
Classifier: Topic :: Scientific/Engineering :: Bio-Informatics
Classifier: Operating System :: OS Independent
Classifier: License :: OSI Approved :: MIT License
Classifier: Programming Language :: Python
Classifier: Programming Language :: Python :: 3.9
Classifier: Programming Language :: Python :: 3.10
Classifier: Programming Language :: Python :: 3.11
Classifier: Programming Language :: Python :: 3.12
Requires-Python: >=3.9
License-File: LICENSE
Requires-Dist: cython
Requires-Dist: numpy>=1.10
Requires-Dist: click>=6.6
Requires-Dist: scipy>=1.7.0
Requires-Dist: pandas>=1.3.4
Requires-Dist: pysam>=0.15.0
Requires-Dist: pyyaml
Requires-Dist: bioframe>=0.3.3
Provides-Extra: doc
Requires-Dist: sphinx-click; extra == "doc"
Requires-Dist: ipython; extra == "doc"
Requires-Dist: nbsphinx; extra == "doc"
Requires-Dist: Sphinx>=7.0; extra == "doc"
Requires-Dist: sphinx-rtd-theme; extra == "doc"
Requires-Dist: docutils>0.16; extra == "doc"
Provides-Extra: test
Requires-Dist: pytest; extra == "test"
Requires-Dist: pytest-flake8; extra == "test"
Requires-Dist: pytest-cov; extra == "test"
